{
  "id": "basics-series-circuit",
  "title": "Your First Series Circuit",
  "conceptTags": ["voltage", "current", "resistance"],
  "learningObjectives": [
    "Understand what a series circuit is",
    "Use Ohm's Law to predict current",
    "Observe how adding resistance changes current"
  ],
  "introText": "In a series circuit, components are connected one after another in a single loop. All the current flows through every component. Let's build one and see Ohm's Law in action!",
  "componentPalette": ["dc-source", "resistor", "wire"],
  "steps": [
    {
      "id": "step-1-source",
      "instructionText": "Start by placing a DC Voltage Source on the workspace. Set it to 9V.",
      "targetCondition": {
        "metric": "voltage",
        "operator": "eq",
        "value": 9
      },
      "feedbackOnSuccess": "Great! You've added a 9V source — that's like a 9V battery.",
      "feedbackOnFailure": "Place a DC Voltage Source and make sure it's set to 9 Volts."
    },
    {
      "id": "step-2-resistor",
      "instructionText": "Now add a Resistor and connect it to the voltage source. Set the resistance to 100Ω.",
      "targetCondition": {
        "metric": "validCircuit",
        "operator": "eq",
        "value": true
      },
      "feedbackOnSuccess": "You've completed the circuit! Current is now flowing.",
      "feedbackOnFailure": "Connect the resistor to the voltage source using the terminal dots on each component."
    },
    {
      "id": "step-3-observe",
      "instructionText": "Look at the Circuit Analysis panel. With 9V and 100Ω, the current should be 90 mA (I = V/R = 9/100 = 0.09A).",
      "targetCondition": {
        "metric": "current",
        "operator": "gt",
        "value": 0.05
      },
      "feedbackOnSuccess": "Exactly! Ohm's Law tells us: Current = Voltage ÷ Resistance.",
      "feedbackOnFailure": "Check that your source is 9V and your resistor is 100Ω. The current should be around 0.09A."
    },
    {
      "id": "step-4-add-resistor",
      "instructionText": "Add a second 100Ω resistor in series. What happens to the current? (Hint: total resistance doubles!)",
      "targetCondition": {
        "metric": "resistance",
        "operator": "gte",
        "value": 200
      },
      "feedbackOnSuccess": "The total resistance is now 200Ω, and the current dropped to 45 mA. In a series circuit, resistances add up!",
      "feedbackOnFailure": "Add another resistor (100Ω) and connect it in the series loop. The total resistance should reach 200Ω or more."
    }
  ],
  "assessment": {
    "questions": [
      {
        "id": "q1",
        "questionText": "In a series circuit with a 12V source and a 600Ω resistor, what is the current?",
        "options": ["0.02A (20 mA)", "0.2A (200 mA)", "2A", "7200A"],
        "correctIndex": 0,
        "explanation": "Using Ohm's Law: I = V/R = 12/600 = 0.02A = 20 mA."
      },
      {
        "id": "q2",
        "questionText": "You have two resistors in series: 150Ω and 350Ω. What is the total resistance?",
        "options": ["200Ω", "350Ω", "500Ω", "52500Ω"],
        "correctIndex": 2,
        "explanation": "In a series circuit, resistances simply add up: 150 + 350 = 500Ω."
      },
      {
        "id": "q3",
        "questionText": "If you increase the resistance in a series circuit while keeping voltage the same, what happens to the current?",
        "options": [
          "Current increases",
          "Current decreases",
          "Current stays the same",
          "The circuit breaks"
        ],
        "correctIndex": 1,
        "explanation": "From Ohm's Law (I = V/R), if R goes up and V stays the same, I must go down. Resistance and current have an inverse relationship."
      }
    ]
  }
}
